{
    "nodeGraph": {
        "envelopeVersion": "2021-01-01",
        "packages": [
            {
                "name": "panorama::abstract_rtsp_media_source",
                "version": "1.0"
            },
            {
                "name": "panorama::hdmi_data_sink",
                "version": "1.0"
            },
            {
                "name": "123456789012::application_logic",
                "version": "1.0"
            },
            {
                "name": "123456789012::yolox_s",
                "version": "1.0"
            }
        ],
        "nodes": [
            {
                "name": "camera_node",
                "interface": "panorama::abstract_rtsp_media_source.rtsp_v1_interface",
                "overridable": true,
                "launch": "onAppStart",
                "decorator": {
                    "title": "Camera camera_node",
                    "description": "Default description for camera camera_node"
                }
            },
            {
                "name": "display_node",
                "interface": "panorama::hdmi_data_sink.hdmi0",
                "overridable": false,
                "launch": "onAppStart"
            }
        ],
        "edges": []
    }
}